maGeneLearn/__init__.py
maGeneLearn/cli.py
maGeneLearn/steps/00_split_dataset.py
maGeneLearn/steps/01_chisq_selection.py
maGeneLearn/steps/02_muvr_feature_selection.py
maGeneLearn/steps/03_extract_features.py
maGeneLearn/steps/04_train_model.py
maGeneLearn/steps/05_evaluate_model.py
maGeneLearn/steps/__init__.py
magenelearn-0.2.1.dist-info/licenses/LICENSE
magenelearn-0.2.1.dist-info/METADATA
magenelearn-0.2.1.dist-info/WHEEL
magenelearn-0.2.1.dist-info/entry_points.txt
magenelearn-0.2.1.dist-info/top_level.txt
magenelearn-0.2.1.dist-info/RECORD
