Metadata-Version: 2.4
Name: maGeneLearn
Version: 0.2.1
Summary: A CLI wrapper for the maGeneLean ML pipeline
Home-page: https://github.com/jpaganini/magenelearn
Author: Julian A. Paganini
Author-email: j.a.paganini@uu.nl
Project-URL: Documentation, https://github.com/jpaganini/magenelearn#readme
Project-URL: Source, https://github.com/jpaganini/magenelearn
Project-URL: Tracker, https://github.com/jpaganini/magenelearn/issues
Classifier: Programming Language :: Python :: 3
Classifier: License :: OSI Approved :: MIT License
Classifier: Operating System :: OS Independent
Requires-Python: >=3.9
License-File: LICENSE
Requires-Dist: click==8.1.7
Requires-Dist: pandas==2.1.1
Requires-Dist: numpy==1.24.3
Requires-Dist: scikit-learn==1.3.0
Requires-Dist: imbalanced-learn==0.11.0
Requires-Dist: xgboost==2.0.3
Requires-Dist: joblib==1.2.0
Requires-Dist: shap==0.42.1
Requires-Dist: matplotlib==3.7.2
Requires-Dist: py-muvr==1.0.1
Requires-Dist: optuna==4.5.0
Requires-Dist: tqdm==4.67.1
Requires-Dist: psutil==7.1.0
Dynamic: author
Dynamic: author-email
Dynamic: classifier
Dynamic: description
Dynamic: description-content-type
Dynamic: home-page
Dynamic: license-file
Dynamic: project-url
Dynamic: requires-dist
Dynamic: requires-python
Dynamic: summary
